[
  {
    "artist": "Megadeth",
    "track": "The Blackest Crow",
    "album": "Super Collider",
    "timestamp": "2026-04-03T02:36:42Z",
    "url": "https://www.last.fm/music/Megadeth/_/The+Blackest+Crow"
  },
  {
    "artist": "Megadeth",
    "track": "Beginning Of Sorrow",
    "album": "Super Collider",
    "timestamp": "2026-04-03T02:32:35Z",
    "url": "https://www.last.fm/music/Megadeth/_/Beginning+Of+Sorrow"
  },
  {
    "artist": "Megadeth",
    "track": "Dance In The Rain",
    "album": "Super Collider",
    "timestamp": "2026-04-03T02:26:42Z",
    "url": "https://www.last.fm/music/Megadeth/_/Dance+In+The+Rain"
  },
  {
    "artist": "Megadeth",
    "track": "Off The Edge",
    "album": "Super Collider",
    "timestamp": "2026-04-03T02:22:22Z",
    "url": "https://www.last.fm/music/Megadeth/_/Off+The+Edge"
  },
  {
    "artist": "Megadeth",
    "track": "Built For War",
    "album": "Super Collider",
    "timestamp": "2026-04-03T02:18:08Z",
    "url": "https://www.last.fm/music/Megadeth/_/Built+For+War"
  },
  {
    "artist": "Megadeth",
    "track": "Burn!",
    "album": "Super Collider",
    "timestamp": "2026-04-03T02:14:07Z",
    "url": "https://www.last.fm/music/Megadeth/_/Burn!"
  },
  {
    "artist": "Megadeth",
    "track": "Super Collider",
    "album": "Super Collider",
    "timestamp": "2026-04-03T02:09:57Z",
    "url": "https://www.last.fm/music/Megadeth/_/Super+Collider"
  },
  {
    "artist": "Megadeth",
    "track": "Kingmaker",
    "album": "Super Collider",
    "timestamp": "2026-04-03T02:05:37Z",
    "url": "https://www.last.fm/music/Megadeth/_/Kingmaker"
  },
  {
    "artist": "Howlin’ Wolf",
    "track": "Commit to Crime",
    "album": "I Am the Wolf",
    "timestamp": "2026-04-03T01:53:24Z",
    "url": "https://www.last.fm/music/Howlin%E2%80%99+Wolf/_/Commit+to+Crime"
  },
  {
    "artist": "Howlin’ Wolf",
    "track": "Somebody Walkin' in My House",
    "album": "I Am the Wolf",
    "timestamp": "2026-04-03T01:50:27Z",
    "url": "https://www.last.fm/music/Howlin%E2%80%99+Wolf/_/Somebody+Walkin%27+in+My+House"
  },
  {
    "artist": "Howlin’ Wolf",
    "track": "Goin' Down Slow",
    "album": "I Am the Wolf",
    "timestamp": "2026-04-03T01:47:25Z",
    "url": "https://www.last.fm/music/Howlin%E2%80%99+Wolf/_/Goin%27+Down+Slow"
  },
  {
    "artist": "Howlin’ Wolf",
    "track": "Ain't Superstitious",
    "album": "I Am the Wolf",
    "timestamp": "2026-04-03T01:44:03Z",
    "url": "https://www.last.fm/music/Howlin%E2%80%99+Wolf/_/Ain%27t+Superstitious"
  },
  {
    "artist": "Xaphanak",
    "track": "Versus",
    "album": "Versus",
    "timestamp": "2026-04-02T22:21:30Z",
    "url": "https://www.last.fm/music/Xaphanak/_/Versus"
  },
  {
    "artist": "A3-5",
    "track": "The Last Tree",
    "album": "The Last Tree",
    "timestamp": "2026-04-02T22:19:37Z",
    "url": "https://www.last.fm/music/A3-5/_/The+Last+Tree"
  },
  {
    "artist": "Hard Mind",
    "track": "Fallen Soul",
    "album": "Negative Thoughts",
    "timestamp": "2026-04-02T22:17:35Z",
    "url": "https://www.last.fm/music/Hard+Mind/_/Fallen+Soul"
  },
  {
    "artist": "Rage Against the Machine",
    "track": "Beautiful World",
    "album": "Renegades",
    "timestamp": "2026-04-02T21:58:40Z",
    "url": "https://www.last.fm/music/Rage+Against+the+Machine/_/Beautiful+World"
  },
  {
    "artist": "OFF!",
    "track": "Darkness",
    "album": "First Four EPs",
    "timestamp": "2026-04-02T21:52:53Z",
    "url": "https://www.last.fm/music/OFF!/_/Darkness"
  },
  {
    "artist": "OFF!",
    "track": "Black Thoughts",
    "album": "First Four EPs",
    "timestamp": "2026-04-02T21:51:53Z",
    "url": "https://www.last.fm/music/OFF!/_/Black+Thoughts"
  },
  {
    "artist": "Palehorse",
    "track": "Miserable Heroin Addict vs. Jehovah's Witness Guy",
    "album": "Looking Wet In Public",
    "timestamp": "2026-04-02T20:07:34Z",
    "url": "https://www.last.fm/music/Palehorse/_/Miserable+Heroin+Addict+vs.+Jehovah%27s+Witness+Guy"
  },
  {
    "artist": "Palehorse",
    "track": "Half Lizard / Half Lizard",
    "album": "Looking Wet In Public",
    "timestamp": "2026-04-02T20:02:54Z",
    "url": "https://www.last.fm/music/Palehorse/_/Half+Lizard+%2F+Half+Lizard"
  }
]
