[
  {
    "artist": "Augustus Pablo",
    "track": "Unity Dub",
    "album": "Africa Must Be Free… by 1983 Dub",
    "timestamp": "2026-06-20T06:06:56Z",
    "url": "https://www.last.fm/music/Augustus+Pablo/_/Unity+Dub"
  },
  {
    "artist": "Thelonious Monk",
    "track": "Bemsha Swing",
    "album": "Thelonious Monk Trio",
    "timestamp": "2026-06-20T06:03:49Z",
    "url": "https://www.last.fm/music/Thelonious+Monk/_/Bemsha+Swing"
  },
  {
    "artist": "Culture",
    "track": "Black Rose",
    "album": "Trod On",
    "timestamp": "2026-06-20T06:00:22Z",
    "url": "https://www.last.fm/music/Culture/_/Black+Rose"
  },
  {
    "artist": "Steel Pulse",
    "track": "Back To My Roots",
    "album": "Vex",
    "timestamp": "2026-06-20T05:56:19Z",
    "url": "https://www.last.fm/music/Steel+Pulse/_/Back+To+My+Roots"
  },
  {
    "artist": "Miles Davis",
    "track": "Frelon Brun",
    "album": "Filles de Kilimanjaro",
    "timestamp": "2026-06-20T05:51:01Z",
    "url": "https://www.last.fm/music/Miles+Davis/_/Frelon+Brun"
  },
  {
    "artist": "Augustus Pablo",
    "track": "Please Sunrise",
    "album": "This Is Augustus Pablo",
    "timestamp": "2026-06-20T05:47:09Z",
    "url": "https://www.last.fm/music/Augustus+Pablo/_/Please+Sunrise"
  },
  {
    "artist": "Ornette Coleman",
    "track": "The Circle With a Hole in the Middle",
    "album": "The Art of the Improvisers",
    "timestamp": "2026-06-20T05:43:23Z",
    "url": "https://www.last.fm/music/Ornette+Coleman/_/The+Circle+With+a+Hole+in+the+Middle"
  },
  {
    "artist": "Gregory Isaacs",
    "track": "Objection Overruled",
    "album": "Night Nurse",
    "timestamp": "2026-06-20T05:39:10Z",
    "url": "https://www.last.fm/music/Gregory+Isaacs/_/Objection+Overruled"
  },
  {
    "artist": "Gregory Isaacs",
    "track": "Public Eye's",
    "album": "Slum (In dub)",
    "timestamp": "2026-06-20T05:35:49Z",
    "url": "https://www.last.fm/music/Gregory+Isaacs/_/Public+Eye%27s"
  },
  {
    "artist": "Pharoah Sanders feat. Sedatrius Brown",
    "track": "Village of the Pharoahs, Part Three",
    "album": "Village Of The Pharoahs",
    "timestamp": "2026-06-20T05:32:41Z",
    "url": "https://www.last.fm/music/Pharoah+Sanders+feat.+Sedatrius+Brown/_/Village+of+the+Pharoahs,+Part+Three"
  },
  {
    "artist": "Burning Spear",
    "track": "Marcus Garvey",
    "album": "Marcus Garvey / Garvey’s Ghost",
    "timestamp": "2026-06-20T05:28:36Z",
    "url": "https://www.last.fm/music/Burning+Spear/_/Marcus+Garvey"
  },
  {
    "artist": "Sun Ra",
    "track": "Calling Planet Earth (OVC Session)",
    "album": "Inside The Light World: Sun Ra Meets The OVC",
    "timestamp": "2026-06-20T05:19:57Z",
    "url": "https://www.last.fm/music/Sun+Ra/_/Calling+Planet+Earth+(OVC+Session)"
  },
  {
    "artist": "Alice Coltrane",
    "track": "The Sun",
    "album": "A Monastic Trio",
    "timestamp": "2026-06-20T05:13:56Z",
    "url": "https://www.last.fm/music/Alice+Coltrane/_/The+Sun"
  },
  {
    "artist": "Thelonious Monk",
    "track": "Everything Happens to Me",
    "album": "Solo Monk",
    "timestamp": "2026-06-20T05:10:23Z",
    "url": "https://www.last.fm/music/Thelonious+Monk/_/Everything+Happens+to+Me"
  },
  {
    "artist": "Burning Spear",
    "track": "No More War",
    "album": "Man In The Hills",
    "timestamp": "2026-06-20T05:07:08Z",
    "url": "https://www.last.fm/music/Burning+Spear/_/No+More+War"
  },
  {
    "artist": "Thelonious Monk",
    "track": "Criss Cross",
    "album": "Criss-Cross",
    "timestamp": "2026-06-20T05:03:02Z",
    "url": "https://www.last.fm/music/Thelonious+Monk/_/Criss+Cross"
  },
  {
    "artist": "Thelonious Monk",
    "track": "Suburban Eyes",
    "album": "Genius of Modern Music, Volume 1",
    "timestamp": "2026-06-20T04:59:17Z",
    "url": "https://www.last.fm/music/Thelonious+Monk/_/Suburban+Eyes"
  },
  {
    "artist": "Burning Spear",
    "track": "No War",
    "album": "The Original Burning Spear",
    "timestamp": "2026-06-20T04:56:16Z",
    "url": "https://www.last.fm/music/Burning+Spear/_/No+War"
  },
  {
    "artist": "Miles Davis Quintet",
    "track": "Just Squeeze Me (But Don’t Tease Me)",
    "album": "Porgy and Bess",
    "timestamp": "2026-06-20T04:50:56Z",
    "url": "https://www.last.fm/music/Miles+Davis+Quintet/_/Just+Squeeze+Me+(But+Don%E2%80%99t+Tease+Me)"
  },
  {
    "artist": "John Coltrane",
    "track": "Blues to Elvin",
    "album": "Coltrane Plays the Blues",
    "timestamp": "2026-06-20T04:43:25Z",
    "url": "https://www.last.fm/music/John+Coltrane/_/Blues+to+Elvin"
  }
]
