[
  {
    "artist": "Morphine",
    "track": "Gone for Good",
    "album": "Yes",
    "timestamp": "2026-05-01T06:33:52Z",
    "url": "https://www.last.fm/music/Morphine/_/Gone+for+Good"
  },
  {
    "artist": "Morphine",
    "track": "Free Love",
    "album": "Yes",
    "timestamp": "2026-05-01T06:30:28Z",
    "url": "https://www.last.fm/music/Morphine/_/Free+Love"
  },
  {
    "artist": "Morphine",
    "track": "Sharks",
    "album": "Yes",
    "timestamp": "2026-05-01T06:26:57Z",
    "url": "https://www.last.fm/music/Morphine/_/Sharks"
  },
  {
    "artist": "Morphine",
    "track": "The Jury",
    "album": "Yes",
    "timestamp": "2026-05-01T06:24:51Z",
    "url": "https://www.last.fm/music/Morphine/_/The+Jury"
  },
  {
    "artist": "Morphine",
    "track": "I Had My Chance",
    "album": "Yes",
    "timestamp": "2026-05-01T06:22:03Z",
    "url": "https://www.last.fm/music/Morphine/_/I+Had+My+Chance"
  },
  {
    "artist": "Morphine",
    "track": "Super Sex",
    "album": "Yes",
    "timestamp": "2026-05-01T06:18:49Z",
    "url": "https://www.last.fm/music/Morphine/_/Super+Sex"
  },
  {
    "artist": "Morphine",
    "track": "All Your Way",
    "album": "Yes",
    "timestamp": "2026-05-01T06:15:09Z",
    "url": "https://www.last.fm/music/Morphine/_/All+Your+Way"
  },
  {
    "artist": "Morphine",
    "track": "Yes",
    "album": "Yes",
    "timestamp": "2026-05-01T06:12:46Z",
    "url": "https://www.last.fm/music/Morphine/_/Yes"
  },
  {
    "artist": "Morphine",
    "track": "Whisper",
    "album": "Yes",
    "timestamp": "2026-05-01T06:10:04Z",
    "url": "https://www.last.fm/music/Morphine/_/Whisper"
  },
  {
    "artist": "Morphine",
    "track": "Radar",
    "album": "Yes",
    "timestamp": "2026-05-01T06:07:58Z",
    "url": "https://www.last.fm/music/Morphine/_/Radar"
  },
  {
    "artist": "Morphine",
    "track": "Scratch",
    "album": "Yes",
    "timestamp": "2026-05-01T06:04:45Z",
    "url": "https://www.last.fm/music/Morphine/_/Scratch"
  },
  {
    "artist": "Morphine",
    "track": "Honey White",
    "album": "Yes",
    "timestamp": "2026-05-01T06:01:38Z",
    "url": "https://www.last.fm/music/Morphine/_/Honey+White"
  },
  {
    "artist": "Morphine",
    "track": "I Had My Chance",
    "album": "Yes",
    "timestamp": "2026-05-01T02:03:30Z",
    "url": "https://www.last.fm/music/Morphine/_/I+Had+My+Chance"
  },
  {
    "artist": "Morphine",
    "track": "Super Sex",
    "album": "Yes",
    "timestamp": "2026-05-01T02:00:03Z",
    "url": "https://www.last.fm/music/Morphine/_/Super+Sex"
  },
  {
    "artist": "Morphine",
    "track": "All Your Way",
    "album": "Yes",
    "timestamp": "2026-05-01T01:56:36Z",
    "url": "https://www.last.fm/music/Morphine/_/All+Your+Way"
  },
  {
    "artist": "Morphine",
    "track": "Yes",
    "album": "Yes",
    "timestamp": "2026-05-01T01:54:06Z",
    "url": "https://www.last.fm/music/Morphine/_/Yes"
  },
  {
    "artist": "Morphine",
    "track": "Whisper",
    "album": "Yes",
    "timestamp": "2026-05-01T01:51:18Z",
    "url": "https://www.last.fm/music/Morphine/_/Whisper"
  },
  {
    "artist": "Morphine",
    "track": "Radar",
    "album": "Yes",
    "timestamp": "2026-05-01T01:47:56Z",
    "url": "https://www.last.fm/music/Morphine/_/Radar"
  },
  {
    "artist": "Morphine",
    "track": "Scratch",
    "album": "Yes",
    "timestamp": "2026-05-01T01:44:42Z",
    "url": "https://www.last.fm/music/Morphine/_/Scratch"
  },
  {
    "artist": "Morphine",
    "track": "Honey White",
    "album": "Yes",
    "timestamp": "2026-05-01T01:41:33Z",
    "url": "https://www.last.fm/music/Morphine/_/Honey+White"
  }
]
