[
  {
    "artist": "Haken",
    "track": "The Architect",
    "album": "Affinity",
    "timestamp": "2026-05-23T23:09:09Z",
    "url": "https://www.last.fm/music/Haken/_/The+Architect"
  },
  {
    "artist": "Haken",
    "track": "Falling Back To Earth",
    "album": "The Mountain",
    "timestamp": "2026-05-23T02:07:17Z",
    "url": "https://www.last.fm/music/Haken/_/Falling+Back+To+Earth"
  },
  {
    "artist": "Haken",
    "track": "Invasion",
    "album": "Virus",
    "timestamp": "2026-05-23T01:59:50Z",
    "url": "https://www.last.fm/music/Haken/_/Invasion"
  },
  {
    "artist": "Haken",
    "track": "The Endless Knot",
    "album": "Affinity",
    "timestamp": "2026-05-23T01:53:56Z",
    "url": "https://www.last.fm/music/Haken/_/The+Endless+Knot"
  },
  {
    "artist": "Haken",
    "track": "Pareidolia",
    "album": "The Mountain",
    "timestamp": "2026-05-23T01:44:21Z",
    "url": "https://www.last.fm/music/Haken/_/Pareidolia"
  },
  {
    "artist": "Haken",
    "track": "The Good Doctor",
    "album": "Vector",
    "timestamp": "2026-05-23T01:38:25Z",
    "url": "https://www.last.fm/music/Haken/_/The+Good+Doctor"
  },
  {
    "artist": "Haken",
    "track": "The Path",
    "album": "The Mountain",
    "timestamp": "2026-05-23T01:35:17Z",
    "url": "https://www.last.fm/music/Haken/_/The+Path"
  },
  {
    "artist": "Haken",
    "track": "In Memoriam",
    "album": "The Mountain",
    "timestamp": "2026-05-23T01:32:02Z",
    "url": "https://www.last.fm/music/Haken/_/In+Memoriam"
  },
  {
    "artist": "Haken",
    "track": "1985",
    "album": "Affinity",
    "timestamp": "2026-05-23T01:24:46Z",
    "url": "https://www.last.fm/music/Haken/_/1985"
  },
  {
    "artist": "Haken",
    "track": "Initiate",
    "album": "Affinity",
    "timestamp": "2026-05-23T01:18:42Z",
    "url": "https://www.last.fm/music/Haken/_/Initiate"
  },
  {
    "artist": "Haken",
    "track": "Bound by Gravity",
    "album": "Affinity",
    "timestamp": "2026-05-22T15:21:26Z",
    "url": "https://www.last.fm/music/Haken/_/Bound+by+Gravity"
  },
  {
    "artist": "Haken",
    "track": "The Endless Knot",
    "album": "Affinity",
    "timestamp": "2026-05-22T15:14:34Z",
    "url": "https://www.last.fm/music/Haken/_/The+Endless+Knot"
  },
  {
    "artist": "Haken",
    "track": "Red Giant",
    "album": "Affinity",
    "timestamp": "2026-05-22T15:08:27Z",
    "url": "https://www.last.fm/music/Haken/_/Red+Giant"
  },
  {
    "artist": "Haken",
    "track": "Earthrise",
    "album": "Affinity",
    "timestamp": "2026-05-22T15:03:07Z",
    "url": "https://www.last.fm/music/Haken/_/Earthrise"
  },
  {
    "artist": "Haken",
    "track": "The Architect",
    "album": "Affinity",
    "timestamp": "2026-05-22T14:28:07Z",
    "url": "https://www.last.fm/music/Haken/_/The+Architect"
  },
  {
    "artist": "Haken",
    "track": "Lapse",
    "album": "Affinity",
    "timestamp": "2026-05-22T14:21:50Z",
    "url": "https://www.last.fm/music/Haken/_/Lapse"
  },
  {
    "artist": "Haken",
    "track": "1985",
    "album": "Affinity",
    "timestamp": "2026-05-22T12:23:39Z",
    "url": "https://www.last.fm/music/Haken/_/1985"
  },
  {
    "artist": "Haken",
    "track": "Initiate",
    "album": "Affinity",
    "timestamp": "2026-05-22T12:17:35Z",
    "url": "https://www.last.fm/music/Haken/_/Initiate"
  },
  {
    "artist": "Ornette Coleman",
    "track": "Una Muy Bonita",
    "album": "Change of the Century",
    "timestamp": "2026-05-22T11:32:30Z",
    "url": "https://www.last.fm/music/Ornette+Coleman/_/Una+Muy+Bonita"
  },
  {
    "artist": "Thelonious Monk",
    "track": "Blue Monk",
    "album": "Thelonious Monk Trio",
    "timestamp": "2026-05-22T11:25:45Z",
    "url": "https://www.last.fm/music/Thelonious+Monk/_/Blue+Monk"
  }
]
