[
  {
    "artist": "Altin Gün",
    "track": "Sevda Olmasaydı",
    "album": "Yol",
    "timestamp": "2025-11-15T22:33:01Z",
    "url": "https://www.last.fm/music/Altin+G%C3%BCn/_/Sevda+Olmasayd%C4%B1"
  },
  {
    "artist": "Derya Yildirim \u0026 Grup Simsek",
    "track": "Sunrise",
    "album": "Dost 1 - EP",
    "timestamp": "2025-11-15T22:04:18Z",
    "url": "https://www.last.fm/music/Derya+Yildirim+\u0026+Grup+Simsek/_/Sunrise"
  },
  {
    "artist": "Derya Yildirim \u0026 Grup Simsek",
    "track": "Hop Çerkez",
    "album": "Dost 1 - EP",
    "timestamp": "2025-11-15T21:59:24Z",
    "url": "https://www.last.fm/music/Derya+Yildirim+\u0026+Grup+Simsek/_/Hop+%C3%87erkez"
  },
  {
    "artist": "Derya Yildirim \u0026 Grup Simsek",
    "track": "Hastane Önü",
    "album": "Dost 1 - EP",
    "timestamp": "2025-11-15T21:52:08Z",
    "url": "https://www.last.fm/music/Derya+Yildirim+\u0026+Grup+Simsek/_/Hastane+%C3%96n%C3%BC"
  },
  {
    "artist": "Derya Yildirim \u0026 Grup Simsek",
    "track": "Deniz Dalgasız olmaz (Dost Version)",
    "album": "Dost 1 - EP",
    "timestamp": "2025-11-15T21:48:31Z",
    "url": "https://www.last.fm/music/Derya+Yildirim+\u0026+Grup+Simsek/_/Deniz+Dalgas%C4%B1z+olmaz+(Dost+Version)"
  },
  {
    "artist": "Derya Yildirim \u0026 Grup Simsek",
    "track": "Haydar Haydar",
    "album": "Dost 1 - EP",
    "timestamp": "2025-11-15T21:44:06Z",
    "url": "https://www.last.fm/music/Derya+Yildirim+\u0026+Grup+Simsek/_/Haydar+Haydar"
  },
  {
    "artist": "Derya Yildirim \u0026 Grup Simsek",
    "track": "The Trip",
    "album": "Dost 1 - EP",
    "timestamp": "2025-11-15T21:39:45Z",
    "url": "https://www.last.fm/music/Derya+Yildirim+\u0026+Grup+Simsek/_/The+Trip"
  },
  {
    "artist": "Derya Yildirim \u0026 Grup Simsek",
    "track": "3,2,2,3",
    "album": "Nem Kaldi - EP",
    "timestamp": "2025-11-15T21:29:24Z",
    "url": "https://www.last.fm/music/Derya+Yildirim+\u0026+Grup+Simsek/_/3,2,2,3"
  },
  {
    "artist": "Derya Yildirim \u0026 Grup Simsek",
    "track": "Nem Kaldi",
    "album": "Nem Kaldi - EP",
    "timestamp": "2025-11-15T21:23:49Z",
    "url": "https://www.last.fm/music/Derya+Yildirim+\u0026+Grup+Simsek/_/Nem+Kaldi"
  },
  {
    "artist": "Ennio Morricone",
    "track": "Vite Cancellate",
    "album": "Il giustiziere (Colonna sonora originale) [Edizione speciale]",
    "timestamp": "2025-11-15T21:16:15Z",
    "url": "https://www.last.fm/music/Ennio+Morricone/_/Vite+Cancellate"
  },
  {
    "artist": "Ennio Morricone",
    "track": "Terroristi!",
    "album": "Il giustiziere (Colonna sonora originale) [Edizione speciale]",
    "timestamp": "2025-11-15T21:04:43Z",
    "url": "https://www.last.fm/music/Ennio+Morricone/_/Terroristi!"
  },
  {
    "artist": "Ennio Morricone",
    "track": "Il Giustiziere",
    "album": "Il giustiziere (Colonna sonora originale) [Edizione speciale]",
    "timestamp": "2025-11-15T20:59:53Z",
    "url": "https://www.last.fm/music/Ennio+Morricone/_/Il+Giustiziere"
  },
  {
    "artist": "Altin Gün",
    "track": "Doktor Civanım",
    "album": "Aşk",
    "timestamp": "2025-11-15T10:09:11Z",
    "url": "https://www.last.fm/music/Altin+G%C3%BCn/_/Doktor+Civan%C4%B1m"
  },
  {
    "artist": "Altin Gün",
    "track": "Güzelliğin On Para Etmez",
    "album": "Aşk",
    "timestamp": "2025-11-15T10:05:24Z",
    "url": "https://www.last.fm/music/Altin+G%C3%BCn/_/Gu%CC%88zellig%CC%86in+On+Para+Etmez"
  },
  {
    "artist": "Altin Gün",
    "track": "Kalk gidelim",
    "album": "Aşk",
    "timestamp": "2025-11-15T10:00:51Z",
    "url": "https://www.last.fm/music/Altin+G%C3%BCn/_/Kalk+gidelim"
  },
  {
    "artist": "Altin Gün",
    "track": "Canım Oy",
    "album": "Aşk",
    "timestamp": "2025-11-15T09:57:27Z",
    "url": "https://www.last.fm/music/Altin+G%C3%BCn/_/Can%C4%B1m+Oy"
  },
  {
    "artist": "Altin Gün",
    "track": "Rakıya Su Katamam",
    "album": "Aşk",
    "timestamp": "2025-11-15T09:53:46Z",
    "url": "https://www.last.fm/music/Altin+G%C3%BCn/_/Rak%C4%B1ya+Su+Katamam"
  },
  {
    "artist": "Altin Gün",
    "track": "Rakıya Su Katamam",
    "album": "Aşk",
    "timestamp": "2025-11-15T09:49:57Z",
    "url": "https://www.last.fm/music/Altin+G%C3%BCn/_/Rak%C4%B1ya+Su+Katamam"
  },
  {
    "artist": "Altin Gün",
    "track": "Çıt Çıt Çedene",
    "album": "Aşk",
    "timestamp": "2025-11-15T09:45:51Z",
    "url": "https://www.last.fm/music/Altin+G%C3%BCn/_/C%CC%A7%C4%B1t+C%CC%A7%C4%B1t+C%CC%A7edene"
  },
  {
    "artist": "Altin Gün",
    "track": "Dere Geliyor",
    "album": "Aşk",
    "timestamp": "2025-11-15T09:42:05Z",
    "url": "https://www.last.fm/music/Altin+G%C3%BCn/_/Dere+Geliyor"
  }
]
