[
  {
    "artist": "Carpenter Brut",
    "track": "Day Stalker",
    "album": "Leather Terror",
    "timestamp": "2026-03-05T06:54:11Z",
    "url": "https://www.last.fm/music/Carpenter+Brut/_/Day+Stalker"
  },
  {
    "artist": "Carpenter Brut feat. Ulver",
    "track": "…Good Night, Goodbye",
    "album": "Leather Terror",
    "timestamp": "2026-03-05T06:50:11Z",
    "url": "https://www.last.fm/music/Carpenter+Brut+feat.+Ulver/_/%E2%80%A6Good+Night,+Goodbye"
  },
  {
    "artist": "Carpenter Brut feat. Greg Puciato",
    "track": "Imaginary Fire",
    "album": "Leather Terror",
    "timestamp": "2026-03-05T06:45:54Z",
    "url": "https://www.last.fm/music/Carpenter+Brut+feat.+Greg+Puciato/_/Imaginary+Fire"
  },
  {
    "artist": "Carpenter Brut feat. GUNSHIP",
    "track": "The Widow Maker",
    "album": "Leather Terror",
    "timestamp": "2026-03-05T06:41:43Z",
    "url": "https://www.last.fm/music/Carpenter+Brut+feat.+GUNSHIP/_/The+Widow+Maker"
  },
  {
    "artist": "Carpenter Brut",
    "track": "Straight Outta Hell",
    "album": "Leather Terror",
    "timestamp": "2026-03-05T06:38:12Z",
    "url": "https://www.last.fm/music/Carpenter+Brut/_/Straight+Outta+Hell"
  },
  {
    "artist": "Carpenter Brut",
    "track": "Opening Title",
    "album": "Leather Terror",
    "timestamp": "2026-03-05T06:29:36Z",
    "url": "https://www.last.fm/music/Carpenter+Brut/_/Opening+Title"
  },
  {
    "artist": "Aswad",
    "track": "Truth",
    "album": "A New Chapter Of Dub",
    "timestamp": "2026-03-05T06:12:02Z",
    "url": "https://www.last.fm/music/Aswad/_/Truth"
  },
  {
    "artist": "Peter Tosh",
    "track": "Legalize It",
    "album": "Legalize It",
    "timestamp": "2026-03-05T06:07:25Z",
    "url": "https://www.last.fm/music/Peter+Tosh/_/Legalize+It"
  },
  {
    "artist": "Mutabaruka",
    "track": "Dispel the Lie",
    "album": "Blakk Wi Blak...K...K...",
    "timestamp": "2026-03-05T06:03:26Z",
    "url": "https://www.last.fm/music/Mutabaruka/_/Dispel+the+Lie"
  },
  {
    "artist": "Dub Syndicate",
    "track": "Pounding System",
    "album": "The Pounding System (Ambience In Dub)",
    "timestamp": "2026-03-05T05:59:31Z",
    "url": "https://www.last.fm/music/Dub+Syndicate/_/Pounding+System"
  },
  {
    "artist": "Black Uhuru",
    "track": "Black Uhuru Anthem",
    "album": "Anthem",
    "timestamp": "2026-03-05T05:54:13Z",
    "url": "https://www.last.fm/music/Black+Uhuru/_/Black+Uhuru+Anthem"
  },
  {
    "artist": "Bad Brains",
    "track": "Banned in D.C.",
    "album": "Bad Brains",
    "timestamp": "2026-03-05T05:50:36Z",
    "url": "https://www.last.fm/music/Bad+Brains/_/Banned+in+D.C."
  },
  {
    "artist": "Aswad",
    "track": "Dub Fire",
    "album": "A New Chapter Of Dub",
    "timestamp": "2026-03-05T05:47:10Z",
    "url": "https://www.last.fm/music/Aswad/_/Dub+Fire"
  },
  {
    "artist": "Lee “Scratch” Perry",
    "track": "Here Come The Warm Dreads",
    "album": "Heavy Rain",
    "timestamp": "2026-03-05T05:42:37Z",
    "url": "https://www.last.fm/music/Lee+%E2%80%9CScratch%E2%80%9D+Perry/_/Here+Come+The+Warm+Dreads"
  },
  {
    "artist": "Augustus Pablo",
    "track": "Stop Them Jah",
    "album": "King Tubbys Meets Rockers Uptown",
    "timestamp": "2026-03-05T05:38:51Z",
    "url": "https://www.last.fm/music/Augustus+Pablo/_/Stop+Them+Jah"
  },
  {
    "artist": "Culture",
    "track": "Callie Weed Song",
    "album": "More Culture",
    "timestamp": "2026-03-05T05:35:36Z",
    "url": "https://www.last.fm/music/Culture/_/Callie+Weed+Song"
  },
  {
    "artist": "Steel Pulse",
    "track": "Global Warning",
    "album": "African Holocaust",
    "timestamp": "2026-03-05T05:31:08Z",
    "url": "https://www.last.fm/music/Steel+Pulse/_/Global+Warning"
  },
  {
    "artist": "Peter Tosh",
    "track": "Why Must I Cry",
    "album": "Legalize It",
    "timestamp": "2026-03-05T05:27:15Z",
    "url": "https://www.last.fm/music/Peter+Tosh/_/Why+Must+I+Cry"
  },
  {
    "artist": "Burning Spear",
    "track": "I Stand Strong",
    "album": "The World Should Know",
    "timestamp": "2026-03-05T05:23:48Z",
    "url": "https://www.last.fm/music/Burning+Spear/_/I+Stand+Strong"
  },
  {
    "artist": "Mutabaruka",
    "track": "I Am de Man",
    "album": "Blakk Wi Blak...K...K...",
    "timestamp": "2026-03-05T05:18:45Z",
    "url": "https://www.last.fm/music/Mutabaruka/_/I+Am+de+Man"
  }
]
